{"name":"SpankBang","description":"SpankBang video platform plugin for Grayjay","platformUrl":"https://www.spankbang.com","author":"GreyPluginDev","authorUrl":"https://github.com/GreyPluginDev","sourceUrl":"https://874cabfb-6513-41be-bf12-3a858f0e65dc-00-r5rrmcbyzwv5.kirk.replit.dev/SpankbangConfig.json","repositoryUrl":"https://github.com/GreyPluginDev/grayjay-plugin-spankbang","scriptUrl":"https://874cabfb-6513-41be-bf12-3a858f0e65dc-00-r5rrmcbyzwv5.kirk.replit.dev/SpankbangScript.js","version":1,"iconUrl":"https://874cabfb-6513-41be-bf12-3a858f0e65dc-00-r5rrmcbyzwv5.kirk.replit.dev/icon.png","id":"a1b2c3d4-e5f6-7890-abcd-ef1234567890","scriptSignature":"","scriptPublicKey":"","packages":["Http"],"allowEval":false,"allowUrls":[".spankbang.com",".spankcdn.com",".sb-cd.com",".sb-cdn.com",".cdn.spankbang.com",".cdn1.spankbang.com",".cdn2.spankbang.com",".cdn3.spankbang.com",".cdn4.spankbang.com"]}